<?xml version = '1.0' encoding = 'UTF-8'?>
<FKIndexAssociation class="oracle.dbtools.crest.model.design.relational.FKIndexAssociation" directorySegmentName="seg_0" id="C0234283-9380-BC43-61A1-727C39DC279F" containerWithKeyObject="2678E0A5-A431-6E5A-E1C2-F84DD05498F3" localFKIndex="6D887006-5055-6E58-93C8-12C96A18FE90" name="Ugovor_Korisnik_Korisnik_FK">
<createdBy>asus</createdBy>
<createdTime>2023-01-27 17:21:38 UTC</createdTime>
<ownerDesignName>Banka</ownerDesignName>
<referredTableLongName>Korisnik</referredTableLongName>
<deleteRule>NO ACTION</deleteRule>
<referredTableID>C6A8058A-6560-8B71-AC55-CC70044A426D</referredTableID>
<keyObject>B141B3AE-C618-63CE-E7A0-C853C1E0B6BD</keyObject>
<referredKeyID>B141B3AE-C618-63CE-E7A0-C853C1E0B6BD</referredKeyID>
<mandatory>true</mandatory>
<refColNames>ID_Korisnika</refColNames>
<transferable>true</transferable>
<rely>false</rely>
<columnDependencyConstraintGenerateInDDL>true</columnDependencyConstraintGenerateInDDL>
</FKIndexAssociation>
